renge/__init__.py
renge/_version.py
renge/renge.py
renge-0.0.2.dist-info/LICENSE
renge-0.0.2.dist-info/METADATA
renge-0.0.2.dist-info/WHEEL
renge-0.0.2.dist-info/top_level.txt
renge-0.0.2.dist-info/RECORD
