Metadata-Version: 2.1
Name: renge
Version: 0.0.2
Summary: Infer gene regulatory networks from time-series single-cell CRISPR data.
Author-email: Masato Ishikawa <masatoiskw@gmail.com>
License: MIT License
Project-URL: Homepage, https://github.com/masastat/RENGE
Project-URL: Bug Tracker, https://github.com/masastat/RENGE/issues
Classifier: Programming Language :: Python :: 3
Classifier: License :: OSI Approved :: MIT License
Classifier: Operating System :: OS Independent
Requires-Python: >=3.7
License-File: LICENSE
Requires-Dist: numpy ==1.19.5
Requires-Dist: pandas ==1.1.5
Requires-Dist: scipy ==1.4.1
Requires-Dist: scikit-learn ==0.21.3
Requires-Dist: statsmodels ==0.10.1
Requires-Dist: jax ==0.2.0
Requires-Dist: optuna ==2.3.0
Requires-Dist: tqdm ==4.60.0
